CHANGELOG.md
mofmt/__init__.py
mofmt/__main__.py
mofmt/collecting/__init__.py
mofmt/collecting/collector.py
mofmt/io/__init__.py
mofmt/io/io.py
mofmt/mofmt.py
mofmt/parsing/__init__.py
mofmt/parsing/generated/__init__.py
mofmt/parsing/generated/Modelica.interp
mofmt/parsing/generated/Modelica.py
mofmt/parsing/generated/Modelica.tokens
mofmt/parsing/generated/ModelicaLexer.interp
mofmt/parsing/generated/ModelicaLexer.py
mofmt/parsing/generated/ModelicaLexer.tokens
mofmt/parsing/generated/ModelicaListener.py
mofmt/parsing/parser.py
mofmt/parsing/parsing.py
mofmt/printing/__init__.py
mofmt/printing/printing.py
mofmt-0.3.6.dist-info/entry_points.txt
mofmt-0.3.6.dist-info/LICENSE
mofmt-0.3.6.dist-info/METADATA
mofmt-0.3.6.dist-info/WHEEL
mofmt-0.3.6.dist-info/RECORD
