Metadata-Version: 2.1
Name: mofmt
Version: 0.3.6
Summary: Modelica Code Formatter
Home-page: https://github.com/ErykMroczek/mofmt
License: MIT
Keywords: Modelica,automation,formatter
Author: Eryk Mroczek
Author-email: mroczek.eryk@gmail.com
Requires-Python: >=3.9,<4.0
Classifier: License :: OSI Approved :: MIT License
Classifier: Programming Language :: Python :: 3
Classifier: Programming Language :: Python :: 3.9
Classifier: Programming Language :: Python :: 3.10
Classifier: Programming Language :: Python :: 3.11
Requires-Dist: antlr4-python3-runtime (==4.13.0)
Project-URL: Repository, https://github.com/ErykMroczek/mofmt
Project-URL: changelog, https://github.com/ErykMroczek/mofmt/blob/main/CHANGELOG.md
